Metadata-Version: 1.0
Name: dist-probability
Version: 2.0
Summary: Gaussian and Binomial distributions
Home-page: UNKNOWN
Author: Aniket Sharma
Author-email: aniketsharma552@gmail.com
License: UNKNOWN
Platform: UNKNOWN
